panoptes/Panoptes1.py
panoptes/Panoptes2.py
panoptes/Panoptes3.py
panoptes/Panoptes4.py
panoptes/Slicer.py
panoptes/__init__.py
panoptes/accessory.py
panoptes/cnn.py
panoptes/colorstandard.png
panoptes/data_input.py
panoptes/execute.py
panoptes/prep.py
panoptes/requirements.txt
panoptes/sample_label.csv
panoptes/sample_prep.py
panoptes/sample_sep_file.csv
panoptes_he-0.1.17.dist-info/LICENSE
panoptes_he-0.1.17.dist-info/METADATA
panoptes_he-0.1.17.dist-info/WHEEL
panoptes_he-0.1.17.dist-info/top_level.txt
panoptes_he-0.1.17.dist-info/RECORD
