Metadata-Version: 2.1
Name: panoptes-he
Version: 0.1.17
Summary: A multi-resolution CNN to predict cancer histopathologic features
Home-page: https://github.com/rhong3/panoptes-he/
Author: Runyu Hong
Author-email: Runyu.Hong@nyu.edu
License: UNKNOWN
Platform: UNKNOWN
Classifier: Programming Language :: Python :: 3.6
Classifier: License :: OSI Approved :: MIT License
Requires-Dist: easygui (>=0.98)
Requires-Dist: Keras (>=2.2.4)
Requires-Dist: numpy (>=1.17.5)
Requires-Dist: opencv-python (>=4.1.2)
Requires-Dist: openslide-python (>=1.1.1)
Requires-Dist: pandas (>=0.25)
Requires-Dist: Pillow (>=7)
Requires-Dist: scikit-learn (>=0.22)
Requires-Dist: scipy (>=1.3)
Requires-Dist: staintools (>=2.1.2)
Requires-Dist: tensorflow (>=1.11)
Requires-Dist: matplotlib (>=3.1)
